odoo/addons/crm_operating_unit/README.rst
odoo/addons/crm_operating_unit/__init__.py
odoo/addons/crm_operating_unit/__manifest__.py
odoo/addons/crm_operating_unit/i18n/crm_operating_unit.pot
odoo/addons/crm_operating_unit/i18n/es.po
odoo/addons/crm_operating_unit/i18n/es_MX.po
odoo/addons/crm_operating_unit/i18n/fr.po
odoo/addons/crm_operating_unit/i18n/it.po
odoo/addons/crm_operating_unit/models/__init__.py
odoo/addons/crm_operating_unit/models/crm_lead.py
odoo/addons/crm_operating_unit/readme/CONTRIBUTORS.md
odoo/addons/crm_operating_unit/readme/DESCRIPTION.md
odoo/addons/crm_operating_unit/readme/USAGE.md
odoo/addons/crm_operating_unit/security/crm_security.xml
odoo/addons/crm_operating_unit/static/description/icon.png
odoo/addons/crm_operating_unit/static/description/index.html
odoo/addons/crm_operating_unit/tests/__init__.py
odoo/addons/crm_operating_unit/tests/test_crm_operating_unit.py
odoo/addons/crm_operating_unit/views/crm_lead_view.xml
odoo_addon_crm_operating_unit-18.0.1.0.0.2.dist-info/METADATA
odoo_addon_crm_operating_unit-18.0.1.0.0.2.dist-info/WHEEL
odoo_addon_crm_operating_unit-18.0.1.0.0.2.dist-info/top_level.txt
odoo_addon_crm_operating_unit-18.0.1.0.0.2.dist-info/RECORD
